iometrics/__init__.py
iometrics/average_metrics.py
iometrics/cli.py
iometrics/disk.py
iometrics/example.py
iometrics/network.py
iometrics/pytorch_lightning/callbacks.py
iometrics-0.0.8.dist-info/entry_points.txt
iometrics-0.0.8.dist-info/LICENSE
iometrics-0.0.8.dist-info/WHEEL
iometrics-0.0.8.dist-info/METADATA
iometrics-0.0.8.dist-info/RECORD
