Metadata-Version: 2.1
Name: iometrics
Version: 0.0.8
Summary: Network and Disk I/O Stats Monitor
Home-page: https://github.com/elgalu/iometrics
License: Apache 2.0
Keywords: io,network,disk,metrics,pytorch-lightning
Author: Leo Gallucci
Author-email: elgalu3@gmail.com
Requires-Python: >=3.7,<4.0
Classifier: Development Status :: 4 - Beta
Classifier: Environment :: Console
Classifier: Intended Audience :: Developers
Classifier: Intended Audience :: Information Technology
Classifier: Intended Audience :: System Administrators
Classifier: License :: OSI Approved :: Apache Software License
Classifier: License :: Other/Proprietary License
Classifier: Operating System :: POSIX :: Linux
Classifier: Programming Language :: Python :: 3
Classifier: Programming Language :: Python :: 3 :: Only
Classifier: Programming Language :: Python :: 3.10
Classifier: Programming Language :: Python :: 3.7
Classifier: Programming Language :: Python :: 3.8
Classifier: Programming Language :: Python :: 3.9
Classifier: Programming Language :: Python :: Implementation
Classifier: Programming Language :: Python :: Implementation :: CPython
Classifier: Topic :: Software Development :: Testing
Classifier: Topic :: Software Development :: Testing :: Acceptance
Classifier: Topic :: Software Development :: Testing :: Mocking
Classifier: Topic :: System :: Emulators
Classifier: Topic :: Utilities
Classifier: Typing :: Typed
Requires-Dist: psutil (>=5.8.0,<6.0.0)
Project-URL: Changelog, https://github.com/elgalu/iometrics/blob/main/CHANGELOG.md
Project-URL: Issues, https://github.com/elgalu/iometrics/issues
Project-URL: Repository, https://github.com/elgalu/iometrics
